openjpeg/__init__.py
openjpeg/_openjpeg.c
openjpeg/_openjpeg.pyx
openjpeg/_version.py
openjpeg/py.typed
openjpeg/tests/__init__.py
openjpeg/tests/README.md
openjpeg/tests/test_decode.py
openjpeg/tests/test_encode.py
openjpeg/tests/test_handler.py
openjpeg/tests/test_misc.py
openjpeg/tests/test_parameters.py
openjpeg/utils.py
_openjpeg.cp311-win_amd64.pyd
pylibjpeg_openjpeg-2.3.0.dist-info/entry_points.txt
pylibjpeg_openjpeg-2.3.0.dist-info/LICENSE
pylibjpeg_openjpeg-2.3.0.dist-info/METADATA
pylibjpeg_openjpeg-2.3.0.dist-info/WHEEL
pylibjpeg_openjpeg-2.3.0.dist-info/RECORD
