Metadata-Version: 2.1
Name: pylibjpeg-openjpeg
Version: 2.3.0
Summary: A Python wrapper for openjpeg, with a focus on use as a plugin for for pylibjpeg
Home-page: https://github.com/pydicom/pylibjpeg-openjpeg
License: MIT
Keywords: dicom pydicom python imaging jpg jpeg jpeg2k jpeg2000 pylibjpeg openjpeg
Author: pylibjpeg-openjpeg contributors
Maintainer: scaramallion
Maintainer-email: scaramallion@users.noreply.github.com
Requires-Python: >=3.8,<4.0
Classifier: Development Status :: 5 - Production/Stable
Classifier: Intended Audience :: Developers
Classifier: Intended Audience :: Healthcare Industry
Classifier: Intended Audience :: Science/Research
Classifier: License :: OSI Approved :: MIT License
Classifier: Natural Language :: English
Classifier: Operating System :: OS Independent
Classifier: Programming Language :: Python :: 3
Classifier: Programming Language :: Python :: 3.8
Classifier: Programming Language :: Python :: 3.9
Classifier: Programming Language :: Python :: 3.10
Classifier: Programming Language :: Python :: 3.11
Classifier: Programming Language :: Python :: 3.12
Classifier: Topic :: Scientific/Engineering :: Medical Science Apps.
Classifier: Topic :: Software Development :: Libraries
Requires-Dist: numpy
